{
    "java": [{
            "language_id": "5c0e27090c2a55426cf37bb1",
            "word": "abstract"
        },
        {
            "language_id": "5c0e27090c2a55426cf37bb1",
            "word": "catch"
        },
        {
            "language_id": "5c0e27090c2a55426cf37bb1",
            "word": "double"
        },
        {
            "language_id": "5c0e27090c2a55426cf37bb1",
            "word": "final"
        },
        {
            "language_id": "5c0e27090c2a55426cf37bb1",
            "word": "implements"
        },
        {
            "language_id": "5c0e27090c2a55426cf37bb1",
            "word": "native"
        },
        {
            "language_id": "5c0e27090c2a55426cf37bb1",
            "word": "public"
        },
        {
            "language_id": "5c0e27090c2a55426cf37bb1",
            "word": "switch"
        },
        {
            "language_id": "5c0e27090c2a55426cf37bb1",
            "word": "true"
        },
        {
            "language_id": "5c0e27090c2a55426cf37bb1",
            "word": "assert"
        },
        {
            "language_id": "5c0e27090c2a55426cf37bb1",
            "word": "char"
        },
        {
            "language_id": "5c0e27090c2a55426cf37bb1",
            "word": "do"
        },
        {
            "language_id": "5c0e27090c2a55426cf37bb1",
            "word": "finally"
        },
        {
            "language_id": "5c0e27090c2a55426cf37bb1",
            "word": "import"
        },
        {
            "language_id": "5c0e27090c2a55426cf37bb1",
            "word": "new"
        },
        {
            "language_id": "5c0e27090c2a55426cf37bb1",
            "word": "return"
        },
        {
            "language_id": "5c0e27090c2a55426cf37bb1",
            "word": "synchronized"
        },
        {
            "language_id": "5c0e27090c2a55426cf37bb1",
            "word": "try"
        },
        {
            "language_id": "5c0e27090c2a55426cf37bb1",
            "word": "boolean"
        },
        {
            "language_id": "5c0e27090c2a55426cf37bb1",
            "word": "brea"
        },
        {
            "language_id": "5c0e27090c2a55426cf37bb1",
            "word": "byte"
        },
        {
            "language_id": "5c0e27090c2a55426cf37bb1",
            "word": "case"
        },
        {
            "language_id": "5c0e27090c2a55426cf37bb1",
            "word": "class"
        },
        {
            "language_id": "5c0e27090c2a55426cf37bb1",
            "word": "const"
        },
        {
            "language_id": "5c0e27090c2a55426cf37bb1",
            "word": "continue"
        },
        {
            "language_id": "5c0e27090c2a55426cf37bb1",
            "word": "default"
        },
        {
            "language_id": "5c0e27090c2a55426cf37bb1",
            "word": "else"
        },
        {
            "language_id": "5c0e27090c2a55426cf37bb1",
            "word": "enum"
        },
        {
            "language_id": "5c0e27090c2a55426cf37bb1",
            "word": "extends"
        },
        {
            "language_id": "5c0e27090c2a55426cf37bb1",
            "word": "false"
        },
        {
            "language_id": "5c0e27090c2a55426cf37bb1",
            "word": "float"
        },
        {
            "language_id": "5c0e27090c2a55426cf37bb1",
            "word": "for"
        },
        {
            "language_id": "5c0e27090c2a55426cf37bb1",
            "word": "goto"
        },
        {
            "language_id": "5c0e27090c2a55426cf37bb1",
            "word": "if"
        },
        {
            "language_id": "5c0e27090c2a55426cf37bb1",
            "word": "instanceof"
        },
        {
            "language_id": "5c0e27090c2a55426cf37bb1",
            "word": "int"
        },
        {
            "language_id": "5c0e27090c2a55426cf37bb1",
            "word": "interface"
        },
        {
            "language_id": "5c0e27090c2a55426cf37bb1",
            "word": "long"
        },
        {
            "language_id": "5c0e27090c2a55426cf37bb1",
            "word": "null"
        },
        {
            "language_id": "5c0e27090c2a55426cf37bb1",
            "word": "package"
        },
        {
            "language_id": "5c0e27090c2a55426cf37bb1",
            "word": "private"
        },
        {
            "language_id": "5c0e27090c2a55426cf37bb1",
            "word": "protected"
        },
        {
            "language_id": "5c0e27090c2a55426cf37bb1",
            "word": "short"
        },
        {
            "language_id": "5c0e27090c2a55426cf37bb1",
            "word": "static"
        },
        {
            "language_id": "5c0e27090c2a55426cf37bb1",
            "word": "strictfp"
        },
        {
            "language_id": "5c0e27090c2a55426cf37bb1",
            "word": "super"
        },
        {
            "language_id": "5c0e27090c2a55426cf37bb1",
            "word": "this"
        },
        {
            "language_id": "5c0e27090c2a55426cf37bb1",
            "word": "throw"
        },
        {
            "language_id": "5c0e27090c2a55426cf37bb1",
            "word": "throws"
        },
        {
            "language_id": "5c0e27090c2a55426cf37bb1",
            "word": "transient"
        },
        {
            "language_id": "5c0e27090c2a55426cf37bb1",
            "word": "void"
        },
        {
            "language_id": "5c0e27090c2a55426cf37bb1",
            "word": "volatile"
        },
        {
            "language_id": "5c0e27090c2a55426cf37bb1",
            "word": "while"
        },
        {
            "language_id": "5c0e27090c2a55426cf37bb1",
            "word": "main"
        },
        {
            "language_id": "5c0e27090c2a55426cf37bb1",
            "word": "args"
        },
        {
            "language_id": "5c0e27090c2a55426cf37bb1",
            "word": "System"
        },
        {
            "language_id": "5c0e27090c2a55426cf37bb1",
            "word": "out"
        },
        {
            "language_id": "5c0e27090c2a55426cf37bb1",
            "word": "println"
        },
        {
            "language_id": "5c0e27090c2a55426cf37bb1",
            "word": "printf"
        },
        {
            "language_id": "5c0e27090c2a55426cf37bb1",
            "word": "module"
        },
        {
            "language_id": "5c0e27090c2a55426cf37bb1",
            "word": "@override"
        },
        {
            "language_id": "5c0e27090c2a55426cf37bb1",
            "word": "implements"
        },
        {
            "language_id": "5c0e27090c2a55426cf37bb1",
            "word": "getName()"
        },
        {
            "language_id": "5c0e27090c2a55426cf37bb1",
            "word": "import"
        },
        {
            "language_id": "5c0e27090c2a55426cf37bb1",
            "word": "enum"
        },
        {
            "language_id": "5c0e27090c2a55426cf37bb1",
            "word": "abstract"
        },
        {
            "language_id": "5c0e27090c2a55426cf37bb1",
            "word": "catch"
        },
        {
            "language_id": "5c0e27090c2a55426cf37bb1",
            "word": "double"
        },
        {
            "language_id": "5c0e27090c2a55426cf37bb1",
            "word": "final"
        },
        {
            "language_id": "5c0e27090c2a55426cf37bb1",
            "word": "implements"
        },
        {
            "language_id": "5c0e27090c2a55426cf37bb1",
            "word": "native"
        },
        {
            "language_id": "5c0e27090c2a55426cf37bb1",
            "word": "public"
        },
        {
            "language_id": "5c0e27090c2a55426cf37bb1",
            "word": "switch"
        },
        {
            "language_id": "5c0e27090c2a55426cf37bb1",
            "word": "true"
        },
        {
            "language_id": "5c0e27090c2a55426cf37bb1",
            "word": "assert"
        },
        {
            "language_id": "5c0e27090c2a55426cf37bb1",
            "word": "char"
        },
        {
            "language_id": "5c0e27090c2a55426cf37bb1",
            "word": "do"
        },
        {
            "language_id": "5c0e27090c2a55426cf37bb1",
            "word": "finally"
        },
        {
            "language_id": "5c0e27090c2a55426cf37bb1",
            "word": "import"
        },
        {
            "language_id": "5c0e27090c2a55426cf37bb1",
            "word": "new"
        },
        {
            "language_id": "5c0e27090c2a55426cf37bb1",
            "word": "return"
        },
        {
            "language_id": "5c0e27090c2a55426cf37bb1",
            "word": "synchronized"
        },
        {
            "language_id": "5c0e27090c2a55426cf37bb1",
            "word": "try"
        }
    ]
}